PyMathRender/__init__.py
PyMathRender-1.0.2.dist-info/LICENSE
PyMathRender-1.0.2.dist-info/METADATA
PyMathRender-1.0.2.dist-info/WHEEL
PyMathRender-1.0.2.dist-info/top_level.txt
PyMathRender-1.0.2.dist-info/RECORD
