Metadata-Version: 2.1
Name: PyMathRender
Version: 1.0.2
Summary: Pretty rendering method for mathematic functions
Home-page: https://github.com/donno2048/Maths
Author: Elisha Hollander
License: MIT
Platform: UNKNOWN
Classifier: Programming Language :: Python :: 3
License-File: LICENSE
Requires-Dist: matplotlib (>=3.4.2)
